ndx_bipolar_referencing/__init__.py
ndx_bipolar_referencing/spec/ndx-bipolar-referencing.extensions.yaml
ndx_bipolar_referencing/spec/ndx-bipolar-referencing.namespace.yaml
tests/__init__.py
tests/test_ext.py
ndx_bipolar_referencing-0.2.0.dist-info/LICENSE
ndx_bipolar_referencing-0.2.0.dist-info/METADATA
ndx_bipolar_referencing-0.2.0.dist-info/WHEEL
ndx_bipolar_referencing-0.2.0.dist-info/top_level.txt
ndx_bipolar_referencing-0.2.0.dist-info/RECORD
