Metadata-Version: 2.1
Name: ndx-bipolar-referencing
Version: 0.2.0
Summary: An NWB:N extension for storing bipolar referencing schema
Home-page: https://github.com/ben-dichter-consulting/ndx-bipolar-referencing
Author: Ben Dichter
Author-email: ben.dichter@gmail.com
License: BSD 3-Clause
Platform: UNKNOWN
Classifier: Intended Audience :: Developers
Classifier: Intended Audience :: Science/Research
Requires-Dist: pynwb (>=1.1.2)
